Metadata-Version: 1.1
Name: radicale-sirius-plugin
Version: 0.3.0
Summary: Access CVUT Fit Sirius Service using caldav
Home-page: https://github.com/bezstpav/radicale-sirius-plugin
Author: Pavel Bezstarosti
Author-email: bezstpav@fit.cvut.cz
License: MIT
Keywords: radicale,caldav,Sirus
Platform: UNKNOWN
Classifier: Development Status :: 3 - Alpha
Classifier: Intended Audience :: Developers
Classifier: Intended Audience :: Information Technology
Classifier: Intended Audience :: Customer Service
Classifier: License :: OSI Approved :: MIT License
Classifier: Natural Language :: English
Classifier: Programming Language :: Python
Classifier: Programming Language :: Python :: 3.7
Classifier: Topic :: Utilities
Classifier: Topic :: Software Development :: Libraries :: Python Modules
